{
  "shortId": "KRY",
  "name": "色 玖竜",
  "enName": "SHIKI KURYU",
  "thumbnailUrl": "/images/ShikiKuryu/sprite/ShikiKuryu_sprite_1.png",
  "colorPalette": ["#1F4E22", "#A1F900", "#E7FF11"],
  "backgroundUrl": "https://sakuranouta.biz/wp-content/uploads/2023/10/%E9%AD%94%E6%B3%95%E4%BD%BF%E3%81%84%E3%81%AE%E9%83%A8%E5%B1%8B_6_%E3%82%A2%E3%83%BC%E3%83%88%E3%83%9C%E3%83%BC%E3%83%89-1-1024x576.jpg",
  "profile": {
    "description": "ごく普通の、根暗な高校生。\n学力は中の下。可もなく不可もなく。\nどこかこの世の全てに対して諦めているような、そんな眼差しで日々を過ごす。\n\n母は名も知れない舞台役者。\nそのため、幼少期より舞台上で輝く母に憧れがあった。\n小学生の時の演劇で与えられた悪役を懸命に演じると、同級生に「気持ち悪い」と一蹴される。\n以降、演劇に対して憧れがありつつも、トラウマを抱えている。\n",
    "age": 17,
    "gender": "男",
    "height": "172cm",
    "weight": "53kg",
    "job": "高校1年生",
    "birthday": "",
    "from": ""
  },
  "sprites": [
    {
      "iconUrl": "/images/ShikiKuryu/icon/ShikiKuryu_icon_1.png",
      "spriteUrl": "/images/ShikiKuryu/sprite/ShikiKuryu_sprite_1.png"
    },
    {
      "iconUrl": "/images/ShikiKuryu/icon/ShikiKuryu_icon_2.png",
      "spriteUrl": "/images/ShikiKuryu/sprite/ShikiKuryu_sprite_2.png"
    }
  ],
  "status": {
    "type": "エモクロア",
    "身体": 2,
    "器用": 4,
    "精神": 4,
    "五感": 6,
    "知力": 4,
    "魅力": 3,
    "社会": 2,
    "運勢": 3
  },
  "skills": {
    "洞察": "Lv.2",
    "直感": "Lv.2",
    "観察眼": "Lv.2",
    "聞き耳": "Lv.1",
    "毒見": "Lv.1",
    "危機察知": "Lv.2",
    "★霊感": "Lv.1",
    "ディベート": "Lv.2",
    "隠匿": "Lv.1"
  },

  "histories": [
    {
      "title": "私のエトワール",
      "comment": "おい、そこのバカとアホ。声の出し方違ぇぞ。\n大体な、発声が成ってねぇから声が響かねえんだよ。下腹部のここを意k...\nってうるせぇ！闇雲に声張れって言ってんじゃねぇよ！",
      "iconUrl": "/images/ShikiKuryu/icon/ShikiKuryu_icon_1.png",
      "companions": [
        {
          "name": "鳳　翼",
          "enName": "OTORI TSUBASA",
          "color": "#F36464",
          "iconUrl": "/images/ShikiKuryu/companions/otori.png",
          "nickName": "鳳"
        },
        {
          "name": "迅本 烈火",
          "enName": "JINMOTO REKKA",
          "color": "#547BE3",
          "iconUrl": "/images/ShikiKuryu/companions/jinmoto.png",
          "nickName": "迅本"
        }
      ]
    }
  ],
  "qaList": [
    {
      "iconUrl": "/images/icon_にせもの3.jpg",
      "answer": "フン、休日は休日なのだから、俺の好きなように過ごすに決まっているだろう！"
    },
    {
      "iconUrl": "/images/icon_にせもの3.jpg",
      "answer": "海か山、どちらかが良いなどとは愚かな質問だな！海にも山にも両方に良い所があるに決まっているだろう！"
    },
    {
      "iconUrl": "/images/icon_にせもの3.jpg",
      "answer": "願い事を叶えてほしいなどとは、俺に失礼な質問だな！"
    },
    {
      "iconUrl": "/images/icon_にせもの3.jpg",
      "answer": "地球が滅亡するなどとは愚かな考えだな！そんなことは起こらないに決まっているだろう！なぜなら、地球が滅亡するのなら、地球が滅亡しないようにするからだ！"
    }
  ],
  "comment": "自由記述",
  "artGallery": []
}
